WSDL/Webservice.xml
WSDL/Homologacao/HAgudoRS-PRONIN.wsdl
WSDL/Homologacao/HAlagoinhasBA-WebISS.wsdl
WSDL/Homologacao/HAlemParaibaMG-PORTALFACIL_ACTCON.wsdl
WSDL/Homologacao/HAlvaresMachadoSP-PRONIN.wsdl
WSDL/Homologacao/HAmargosaBA-ADM_SISTEMAS.wsdl
WSDL/Homologacao/HAmericanaSP-TIPLAN.wsdl
WSDL/Homologacao/HAndradasMG-GOVDIGITAL.wsdl
WSDL/Homologacao/HAndradinaSP-cancelarnfse.wsdl
WSDL/Homologacao/HAndradinaSP-consultarnfseporrps.wsdl
WSDL/Homologacao/HAndradinaSP-recepcionarloterpssincrono.wsdl
WSDL/Homologacao/HAparecidaGoianiaGO-ISSNET.wsdl
WSDL/Homologacao/HAracajuSE-WEBISS.wsdl
WSDL/Homologacao/HArarasSP-SIMPLISS.wsdl
WSDL/Homologacao/HArcosMG-WebISS.wsdl
WSDL/Homologacao/HArroioDoSal-PRONIN.wsdl
WSDL/Homologacao/HAstorgaPR-SIMPLISS.wsdl
WSDL/Homologacao/HAvareSP.wsdl
WSDL/Homologacao/HBageRS-WebISS.wsdl
WSDL/Homologacao/HBalnearioCamboriuSC-PUBLICA.wsdl
WSDL/Homologacao/HBaraoDeCotegipeRS-SystemPro.wsdl
WSDL/Homologacao/HBarbacenaMG-WebISS.wsdl
WSDL/Homologacao/HBarraPiraiRJ-WebISS.wsdl
WSDL/Homologacao/HBarrosoMG-SH3.wsdl
WSDL/Homologacao/HBastosSP-PRONIN.wsdl
WSDL/Homologacao/HBelemPA-DSFLoteRps.wsdl
WSDL/Homologacao/HBethaCancelarNFSe.wsdl
WSDL/Homologacao/HBethaConsultarLoteRPS.wsdl
WSDL/Homologacao/HBethaConsultarNFSe.wsdl
WSDL/Homologacao/HBethaConsultarNFSePorRPS.wsdl
WSDL/Homologacao/HBethaConsultarSituacaoLoteRPS.wsdl
WSDL/Homologacao/HBethaRecepcionarLoteRps.wsdl
WSDL/Homologacao/HBomDespachoMG-WebISS.wsdl
WSDL/Homologacao/HCacadorSC-PUBLICA.wsdl
WSDL/Homologacao/HCaceresMT-RLZ_INFORMATICA.wsdl
WSDL/Homologacao/HCamacariBA.wsdl
WSDL/Homologacao/HCampinaGrandePB-WebISS_202.wsdl
WSDL/Homologacao/HCampinasDoSulRS-SystemPro.wsdl
WSDL/Homologacao/HCampinasSP-DFSLoteRps.wsdl
WSDL/Homologacao/HCandeiasBA-WEBISS.wsdl
WSDL/Homologacao/HCanelaRS-SystemPro.wsdl
WSDL/Homologacao/HCascavel-ISSNet.wsdl
WSDL/Homologacao/HCrominiaGO-MEGASOFT.wsdl
WSDL/Homologacao/HCruzeiroDoSulRSCancelamentoNFSe.wsdl
WSDL/Homologacao/HCruzeiroDoSulRSConsultaLoteRPS.wsdl
nfselib_legacy-1.0.0.dist-info/licenses/LICENSE
nfselib_legacy-1.0.0.dist-info/METADATA
nfselib_legacy-1.0.0.dist-info/WHEEL
nfselib_legacy-1.0.0.dist-info/top_level.txt
nfselib_legacy-1.0.0.dist-info/RECORD
